eoslib/__init__.py
eoslib/commands/keys_command.py
eoslib/domain/__init__.py
eoslib/domain/claims.py
eoslib/domain/crypto.py
eoslib/domain/helpers.py
eoslib/domain/jwks.py
eoslib/domain/jwt.py
eoslib/domain/kek.py
eoslib/domain/key_management.py
eoslib/domain/key_store.py
eoslib/domain/public_key.py
eoslib/domain/revocation.py
eoslib/domain/sig.py
eoslib/domain/states.py
eoslib/domain/sym_enc.py
eoslib/domain/types.py
eoslib/domain/value.py
eoslib/queries/__init__.py
eoslib/queries/keys.py
eoslib/util/chronos.py
eoslib/util/encoding_helpers.py
eoslib/util/enum_helpers.py
eoslib/util/env.py
eoslib/util/error.py
eoslib/util/fn.py
eoslib/util/monad.py
eoslib/util/singleton.py
eoslib/util/state_machine.py
eoslib-0.2.0.dist-info/METADATA
eoslib-0.2.0.dist-info/WHEEL
eoslib-0.2.0.dist-info/RECORD
