Metadata-Version: 2.1
Name: eoslib
Version: 0.2.0
Summary: 
Author: Col Perks
Author-email: wild.fauve@gmail.com
Requires-Python: >=3.11,<4.0
Classifier: Programming Language :: Python :: 3
Classifier: Programming Language :: Python :: 3.11
Requires-Dist: metis-crypto (>=0.1.0,<0.2.0)
Requires-Dist: pendulum (>=3.0.0,<4.0.0)
Requires-Dist: pydantic (>=2.5.2,<3.0.0)
Requires-Dist: pymonad (>=2.4.0,<3.0.0)
Requires-Dist: simple-memory-cache (>=1.0.0,<2.0.0)
